cmdname_changer/__init__.py
cmdname_changer-1.0.dist-info/METADATA
cmdname_changer-1.0.dist-info/WHEEL
cmdname_changer-1.0.dist-info/top_level.txt
cmdname_changer-1.0.dist-info/RECORD
