Metadata-Version: 2.1
Name: cmdname-changer
Version: 1.0
Summary: cmd name changer (title)
Author: Anonymous
Author-email: anounymousmail89@gmail.com
Classifier: Programming Language :: Python :: 3
Classifier: License :: OSI Approved :: MIT License
Classifier: Operating System :: OS Independent
